{
  "foodList": [
    {
      "id": 1,
      "food": "rice",
      "price": 8.47,
      "status": "pending"
    },
    {
      "id": 2,
      "food": "beans",
      "price": 78.99,
      "status": "completed"
    },
    {
      "id": 3,
      "food": "plantain",
      "price": 500,
      "status": "completed"
    },
    {
      "id": 4,
      "food": "plantain",
      "price": 500,
      "status": "pending"
    },
    {
      "id": 5,
      "food": "Fried Rice",
      "price": 7700,
      "status": "pending"
    },
    {
      "id": 7,
      "food": "Beans Rice",
      "price": 9700,
      "status": "pending"
    }
  ]
}